attribuutit/__init__.py
attribuutit/__main__.py
attribuutit/attribuutit.py
attribuutit/cli.py
attribuutit/shp.py
attribuutit/tif.py
attribuutit/vpf.py
attribuutit/wbk.py
attribuutit-2025.7.8.dist-info/licenses/LICENSE
attribuutit-2025.7.8.dist-info/METADATA
attribuutit-2025.7.8.dist-info/WHEEL
attribuutit-2025.7.8.dist-info/entry_points.txt
attribuutit-2025.7.8.dist-info/top_level.txt
attribuutit-2025.7.8.dist-info/RECORD
