Metadata-Version: 2.4
Name: attribuutit
Version: 2025.7.8
Summary: Nodes, Edges, Faces, and Attributes (Finnish: "Solmut, reunat, pinnat ja attribuutit").
Author-email: Stefan Hagen <stefan@hagen.link>
Maintainer-email: Stefan Hagen <stefan@hagen.link>
License: MIT License
Project-URL: Homepage, https://git.sr.ht/~sthagen/attribuutit
Project-URL: Bug-Tracker, https://todo.sr.ht/~sthagen/attribuutit
Project-URL: Documentation, https://codes.dilettant.life/docs/attribuutit
Project-URL: Source-Code, https://git.sr.ht/~sthagen/attribuutit
Project-URL: Test-Coverage, https://codes.dilettant.life/coverage/attribuutit
Keywords: attributes,edges,faces,gis-tools,nodes,verification
Classifier: Development Status :: 3 - Alpha
Classifier: Intended Audience :: Developers
Classifier: License :: OSI Approved :: MIT License
Classifier: Programming Language :: Python :: 3.10
Classifier: Programming Language :: Python :: 3.11
Classifier: Programming Language :: Python :: 3.12
Classifier: Programming Language :: Python :: 3.13
Classifier: Programming Language :: Python :: 3.9
Requires-Python: >=3.9
License-File: LICENSE
Requires-Dist: geotiff>=0.2.10
Requires-Dist: pyshp>=2.3.1
Requires-Dist: typer>=0.16.0
Provides-Extra: dev
Requires-Dist: black; extra == "dev"
Requires-Dist: coverage; extra == "dev"
Requires-Dist: hypothesis; extra == "dev"
Requires-Dist: mypy; extra == "dev"
Requires-Dist: pytest; extra == "dev"
Requires-Dist: pytest-cov; extra == "dev"
Requires-Dist: pytest-flake8; extra == "dev"
Requires-Dist: ruff; extra == "dev"
Dynamic: license-file
